alpaca_finance
