Metadata-Version: 2.1
Name: alpaca-finance
Version: 1.1.3
Summary: An unofficial Python3.9+ package that models positions on the Alpaca Finance platform to simplify interaction with their smart contracts in your Python projects.
Home-page: https://github.com/PathX-Projects/Alpaca-Finance-Python
Author: Harrison Schick
Author-email: hschickdevs@gmail.com
License: UNKNOWN
Platform: UNKNOWN
